README.md
setup.py
mbanc_school.egg-info/PKG-INFO
mbanc_school.egg-info/SOURCES.txt
mbanc_school.egg-info/dependency_links.txt
mbanc_school.egg-info/top_level.txt
school/__init__.py
school/classroom.py
school/student.py